tpen2tei/__init__.py
tpen2tei/parse.py
tpen2tei/wordtokenize.py
tpen2tei-1.2.9.dist-info/METADATA
tpen2tei-1.2.9.dist-info/WHEEL
tpen2tei-1.2.9.dist-info/top_level.txt
tpen2tei-1.2.9.dist-info/RECORD
