Metadata-Version: 2.1
Name: tpen2tei
Version: 1.2.9
Summary: A module for conversion of SharedCanvas-JSON transcription data to TEI XML
Home-page: https://github.com/DHUniWien/tpen2tei
Author: Tara L Andrews
Author-email: tla@mit.edu
License: MIT
Keywords: TEI-XML SC-JSON manuscript transcription
Platform: UNKNOWN
Classifier: Development Status :: 3 - Alpha
Classifier: Intended Audience :: Developers
Classifier: Intended Audience :: Science/Research
Classifier: Topic :: Text Processing :: Markup :: XML
Classifier: License :: OSI Approved :: MIT License
Classifier: Programming Language :: Python :: 3
Requires-Python: >3
Requires-Dist: lxml
